inkdna_fingerprint_legacy/__init__.py
inkdna_fingerprint_legacy/__main__.py
inkdna_fingerprint_legacy/stamp_pdf.py
inkdna_fingerprint_legacy/utils.py
inkdna_fingerprint_legacy/verify.py
inkdna_fingerprint_legacy-0.1.3.dist-info/licenses/LICENSE
inkdna_fingerprint_legacy-0.1.3.dist-info/METADATA
inkdna_fingerprint_legacy-0.1.3.dist-info/WHEEL
inkdna_fingerprint_legacy-0.1.3.dist-info/entry_points.txt
inkdna_fingerprint_legacy-0.1.3.dist-info/top_level.txt
inkdna_fingerprint_legacy-0.1.3.dist-info/RECORD
