Metadata-Version: 2.4
Name: inkdna-fingerprint-legacy
Version: 0.1.3
Summary: Simple CLI to stamp and verify PDFs with sidecars (execution-only).
Author: InkDNA
License: MIT
Classifier: Programming Language :: Python :: 3
Classifier: License :: OSI Approved :: MIT License
Classifier: Operating System :: OS Independent
Requires-Python: >=3.9
License-File: LICENSE
Requires-Dist: pikepdf>=9.0.0
Dynamic: license-file
